jupyter_kernel_proxy.py
jupyter_kernel_proxy-1.0.1.dist-info/LICENSE
jupyter_kernel_proxy-1.0.1.dist-info/METADATA
jupyter_kernel_proxy-1.0.1.dist-info/WHEEL
jupyter_kernel_proxy-1.0.1.dist-info/top_level.txt
jupyter_kernel_proxy-1.0.1.dist-info/RECORD
